Metadata-Version: 2.3
Name: swarmauri_evaluator_subprocess
Version: 0.1.2
Summary: A subprocess-based evaluator for executing and measuring program performance in isolated subprocesses
License: Apache-2.0
Keywords: subprocess,evaluation,sandboxing,program execution,resource limits,performance measurement,testing,security,swarm,ai,swarmauri
Author: SwarmAuri Team
Author-email: info@swarmauri.com
Requires-Python: >=3.10,<3.13
Classifier: License :: OSI Approved :: Apache Software License
Classifier: Natural Language :: English
Classifier: Programming Language :: Python :: 3.10
Classifier: Programming Language :: Python :: 3.11
Classifier: Programming Language :: Python :: 3.12
Classifier: Development Status :: 3 - Alpha
Classifier: Intended Audience :: Developers
Classifier: Topic :: Software Development :: Libraries
Classifier: Topic :: Software Development :: Testing
Classifier: Topic :: System :: Monitoring
Requires-Dist: swarmauri_base
Requires-Dist: swarmauri_core
